Workbook

Sheet Schedule
A1: Sl.No. | B1: Module Name | G1: Duration (Days)
A2: 1 | B2: ='Core Java'!B1 -> Core Java Programming | G2: ='Core Java'!B2 -> 10 | H2: M2
A3: 2 | B3: ='CA-HNS'!B1 -> Computer Architecture - Hardware, Network and Software | G3: ='CA-HNS'!B2 -> 1
A4: 3 | B4: =SDLC!B1 -> Software Development Life Cycle and Agile Principles | G4: 1
A5: 4 | B5: Programming Constructs and Algorithms for Problem Solving | G5: 2 | H5: M1
A6: 5 | B6: ='Linux, Shell Scripting and Git'!B1 -> Linux Operating System and Source Code Management with Git | G6: ='Linux, Shell Scripting and Git'!B2 -> 3
A7: 6 | B7: ='RDBMS and SQL'!B1 -> RDBMS and SQL | G7: ='RDBMS and SQL'!B2 -> 3
A8: 7 | B8: =TestingFundamentals!B1 -> Testing Fundamentals | G8: =TestingFundamentals!B2 -> 3 | H8: M2
A9: 8 | B9: ='Selenium&API Testing'!B1 -> Selenium | G9: ='Selenium&API Testing'!B2 -> 10 | H9: M3
A10: 9 | B10: =Docker!B1 -> Container Virtualization with Docker | G10: =Docker!B2 -> 1
A11: 10 | B11: =Ansible!B1 -> Configuration Automation with Ansible | G11: =Ansible!B2 -> 1.5 | H11: M4
A12: 11 | B12: ='DevOps and Jenkins'!B1 -> DevOps and Jenkins | G12: ='DevOps and Jenkins'!B2 -> 1.5
A13: 12 | B13: ='Capstone Project'!B1 -> Capstone Project | G13: 7
A14: TOTAL | G14: =SUM(G2:G13) -> 44

Sheet JAVA
A1: Sl. No. | B1: Topics | C1: Day End Assignment Options | D1: Remarks | E1: Duration (Days)
A2: 1 | B2: Programming Constructs | C2: Assignment 1: Pseudocode Development - Task: Write a detailed pseudocode for a simple program that takes a number as input, calculates the square if it's even or the cube if it's odd, and then outputs the result. Incorporate conditional and looping constructs. Assignment 2: Flowchart Creation - Design a flowchart that outlines the logic for a user login process. It should include conditional paths for successful and unsuccessful login attempts, and a loop that allows a user three attempts before locking the account. Assignment 3: Function Design and Modularization - Create a document that describes the design of two modular functions: one that returns the factorial of a number, and another that calculates the nth Fibonacci number. Include pseudocode and a brief explanation of how modularity in programming helps with code reuse and organization. | D2: Learners will grasp basic programming constructs and programming logic essential for developing a systematic approach to problem-solving in programming. They will be introduced to conditional and looping constructs, critical for directing program flow. Flowcharts will help visualize and design logical sequences, an essential skill for effective programming. They will explore logical operators and decision trees, crucial for making decisions in programming. Understanding these concepts is key to developing efficient and effective problem-solving strategies in software development. They will learn to use functions, promoting modularity in programming. This concept is vital for writing clean, reusable, and well-organized code, a fundamental skill in software development. | E2: 1
A3: 1.1 | B3: Introduction to Programming Constructs
B4: Overview of Programming Constructs
B5: Variables, Expressions, and Statements
B6: Introduction to Pseudocode
B7: Pseudocode for Common Algorithms
B8: Sorting algorithms: Bubble, Selection, Insertion Sort
B9: Searching algorithms: Linear Search, Binary Search
A10: 1.2 | B10: Control Flow Constructs and Flowcharts
B11: Conditional Constructs: If, Else, Switch
B12: Looping Constructs: For, While, Do-While
B13: Creating and Interpreting Flowcharts
A14: 1.3 | B14: Efficient Flowcharting Techniques
B15: Using Subroutines in Flowcharts for Repeated Actions
B16: Flowchart Symbols for Concurrency and Synchronization
A17: 1.4 | B17: Logical Thinking with Operators and Decision Trees
B18: Logical Operators: AND, OR, NOT
B19: Decision Trees for Problem Solving
B20: Flowchart Design for Decision Making Processes
A21: 1.5 | B21: Functions and Modular Design
B22: Fundamentals of Function Design
B23: Modular Programming Concepts
B24: Writing Pseudocode for Modular Functions
A25: 2 | B25: Algorithms and Problem-Solving ---> Need to start after completing String Handling | C25: Assignment 1: Pseudocode and Flowchart for Sorting Algorithm - Write pseudocode and create a flowchart for a bubble sort algorithm. Provide a brief explanation of how the algorithm works and a simple array of integers to demonstrate a dry run of your algorithm. | D25: Learn basic sorting algorithms and the use of pseudocode and flowcharts for algorithm design essential for understanding algorithmic thinking and developing effective problem-solving strategies in computing. Understand problem analysis and implementing search algorithms to understand how to approach and solve problems algorithmically, a critical skill in software development and computational thinking. | E25: Need to start after completing String Handling
A26: 2.1 | B26: Basic Algorithms with Pseudocode and Flowcharts using "http://www.flowgorithm.org/"
B27: Algorithmic Thinking and Pseudocode
B28: Introduction to Sorting Algorithms: Bubble Sort and Insertion Sort
B29: Designing Flowcharts for Sorting Algorithms
A30: 2.2 | B30: Algorithmic Problem Solving
B31: Problem Analysis for Algorithmic Solutions
B32: Implementing Search Algorithms: Linear Search and Binary Search
B33: Writing and Visualizing Search Algorithms
A34: 2.6 | B34: Practical Application of Algorithms
B35: Application of Sorting and Searching Algorithms in Real-world Scenarios
B36: Dry Run: Step-by-Step Algorithm Testing
B37: Group Problem Solving and Algorithm Implementation
A39: Sl. No. | B39: Topics | C39: Remarks | D39: Duration (Days)
A40: 1 | B40: Java Fundamentals | C40: Learner will understand the essentials of setting up a Java development environment and the syntax required to write Java programs. They'll learn to configure tools like JDK and IDEs, which are vital for code development and execution. | D40: 1.5
A41: 1.1 | B41: Java Environment Setup
B42: Installing JDK
B43: Configuring IDEs (Eclipse, IntelliJ IDEA)
A44: 1.2 | B44: Java Syntax and Basic Constructs
B45: Primitive Data Types and Variables
B46: Operators and their Precedence
B47: Control Flow Statements (if, switch, loops - for, while, do-while)
A48: 2 | B48: Arrays in Java
A49: 2.1 | B49: Definition and characteristics | C49: Building on their understanding of functions in Java, learners will apply this foundational knowledge to arrays, understanding their structure and manipulation. They will work with array operations—accessing, inserting, deleting, updating, and reversing elements—to grasp basic data handling. Learners will also explore sorting algorithms, starting with brute force methods, and searching techniques, such as the linear search, to find elements efficiently. This combination of array manipulation and algorithmic thinking is critical for practical applications in software development, enabling learners to manage and process data effectively in real-world programming scenarios. | D49: 2.5
A50: 2.2 | B50: Implement Basic operations
B51: Access
B52: Insert
B53: Delete
B54: Update
B55: Reverse
B56: Slice
A57: 2.3 | B57: Sorting an Array - Brute Force Method
A58: 2.4 | B58: Searching an Array - Linear Search Method
A59: 3 | B59: String Handling | C59: Additionally, skills in string manipulation through various String class methods and the performance benefits of StringBuilder and StringBuffer are emphasized.
A60: 3.1 | B60: String Manipulation: Methods in the String Class
B61: StringBuilder and StringBuffer: Mutability and Performance
A62: 4 | B62: Java Object-Oriented Programming (OOP) Basics | C62: The engineer will also delve into the core principles of object-oriented programming, understanding classes, objects, and inheritance, which are fundamental in crafting structured and maintainable code. Additionally, they will acquire skills in managing code execution flow and error handling through control statements and exception handling, crucial for building robust applications. | D62: 2
A63: 4.1 | B63: Object-Oriented Programming (OOP)
B64: Classes and Objects: Definitions and Differences
B65: Constructors: Purpose and Types
B66: Encapsulation: Access Modifiers and Getters/Setters
B67: Inheritance: Superclass and Subclass Relationships
B68: Polymorphism: Method Overloading and Overriding
A69: 4.2 | B69: Organizing Code
B70: Packages: Creating and Using Packages
B71: Classpath: Understanding and Setting the Classpath
B72: Java Modules: Modular Programming in Java
A73: 5 | B73: Exception Handling
A74: 5.1 | B74: Exception Handling
B75: try-catch Blocks: Basic Exception Handling
B76: Creating Custom Exceptions: When and How to Create
A77: 6 | B77: Java Collections Framework and Generics | C77: Learner will learn to efficiently manage data in Java using the Collections Framework, mastering arrays, lists, sets, maps, and their respective interfaces and implementations. They will also understand generics for type-safe operations. Proficiency in iterators and comparators for collection traversal and sorting is covered. | D77: 2
A78: 6.1 | B78: Arrays: Declaration, Initialization, and Usage
B79: Introduction to List interface.
B80: Exploring ArrayList and LinkedList.
A81: 6.2 | B81: Understanding the Set interface.
B82: Working with HashSet, LinkedHashSet, and TreeSet.
B83: Differentiating between various Set implementations.
A84: 6.3 | B84: Introduction to Map interface.
B85: Exploring HashMap, LinkedHashMap, and TreeMap.
B86: Key-value pair management and use cases.
A87: 6.4 | B87: Iterators and Comparators
A88: 7 | B88: Logic building program practice | C88: Minimum 10 Logic Building program should have been completed by Day 9 (Medium and complex problem statement similar to the platforms like leetcode/Codility/Mettl/ hackerrank/Edabit/Exercism/….) https://leetcode.com/problemset/ https://www.hackerrank.com/domains/python?filters%5Bdifficulty%5D%5B%5D=medium | D88: 1

Sheet CA-HNS
A1: Module | B1: Computer Architecture - Hardware, Network and Software
A2: Duration (Days) | B2: =SUM(E5:E36) -> 1
A4: Sl. No. | B4: Topics | C4: Day End Assignment Options | D4: Remarks | E4: Duration (Days)
A5: 1 | B5: Understanding Computer Architecture | C5: Assignment 1: Draw your Home Network Topology and explain how you are accessing the RPS Lab environment. Assignment 2: Identify a real-world application for both parallel computing and networked systems. Explain how these technologies are used and why they are important in that context. Submission Guidelines: 1. Ensure that each answer is clear, concise, and reflects an understanding of the core concepts. 2. Diagrams can be hand-drawn and scanned or created using any digital drawing tool. 3. Provide references for any external sources used. Submit your work in a single PDF document by end of Module | D5: Understanding the System from a Software Developer perspective, the learners must understand different components of a modern computing device (Computers, Mobiles, Embedded Systems, Intelligent Systems etc.). How the differents parts of the system function, how the data is stored and retrieved. How parallel computing works, different computing solutions for solving complex problems with parallel computing. How data is moved in paralled systems. | E5: 0.5
A6: 1.1 | B6: Introduction to Computer Architecture
B7: Overview of computer architecture.
B8: Importance in software development.
B9: Basic terminology.
A10: 1.2 | B10: Central Processing Unit (CPU)
B11: CPU components and functions.
B12: How a CPU executes instructions.
B13: CPU performance factors.
A14: 1.3 | B14: Memory Hierarchy
B15: Types of memory (RAM, Cache, Hard Drives).
B16: How data is stored and accessed.
B17: Memory management concepts.
A18: 1.4 | B18: Input/Output Systems
B19: Overview of I/O systems.
B20: Communication between CPU, memory, and I/O devices.
B21: Introduction to buses and data transfer.
A22: 1.5 | B22: Basic Concepts in Parallelism and Hardware Acceleration
B23: Introduction to parallel computing.
B24: Multi-core processors and GPUs.
B25: Real-world applications and examples.
A26: 2 | B26: Understanding Computer Networking | D26: Understanding the Networks from a Software Developer perspective, the learners must understand how computer network works, how data is transferred across two connected systems in a network, different addressing schemes. What are protocols, commonly used protocols and their use. How does network isolation and topology work, how data traverses over internet, what is NAT and why they must know it. Understand network security, firewall, VPN etc. | E26: 0.5
A27: 2.1 | B27: Introduction to Networking
B28: Basic networking concepts.
B29: Importance in software development and communication.
A30: 2.2 | B30: Network Models and Protocols
B31: OSI and TCP/IP models.
B32: Common protocols: HTTP, FTP, TCP, UDP.
A33: 2.3 | B33: IP Addressing and Subnets
B34: IPv4 vs. IPv6.
B35: Subnetting basics.
B36: Network Address Translation (NAT).

Sheet SDLC
A1: Module | B1: Software Development Life Cycle and Agile Principles
A2: Duration (Days) | B2: 1
A4: Sl. No. | B4: Topics | C4: Day End Assignment Options | D4: Remarks | E4: Duration (Days)
A5: 1 | B5: Introduction to SDLC Phases | C5: Assignment 1: SDLC Overview - Create a one-page infographic that outlines the SDLC phases (Requirements, Design, Implementation, Testing, Deployment), highlighting the importance of each phase and how they interconnect. Assignment 2: Requirements Gathering - Conduct a 30-minute mock interview to gather requirements for a fictional app that helps organize community events. Summarize the requirements and how you would document and trace them in a one-page brief. Assignment 3: Agile Principles Application - Write a two-paragraph reflection on how the Agile values of individuals and interactions, working solutions, and customer collaboration apply to the development of the community event app. Assignment 4: Scrum Framework Overview - Prepare a one-page cheat sheet on the Scrum framework that includes roles, responsibilities, artifacts, and ceremonies. Provide a brief example of a Sprint task list for the earlier mentioned app project. Submission Guidelines: 1. Ensure that each answer is clear, concise, and reflects an understanding of the core concepts. 2. Diagrams can be hand-drawn and scanned or created using any digital drawing tool. 3. Provide references for any external sources used. Submit your work in a single PDF document by end of Module. | D5: Learners will gain a solid grasp of the Software Development Life Cycle (SDLC), covering its core phases: Requirements, Design, Implementation, Testing, and Deployment. This understanding is essential as it allows learners to effectively participate in software development processes, ensuring they can contribute meaningfully to projects by following the structured path from idea to product. Acquiring a good understanding of SDLC basics is crucial for navigating software development successf | E5: 0.5
A6: 1.1 | B6: Overview of SDLC
B7: Explanation of SDLC phases: Requirements, Design, Implementation, Testing, Deployment.
B8: The significance of a well-defined SDLC.
A9: 1.2 | B9: Requirements Gathering
B10: Techniques for gathering requirements (interviews, surveys, observations).
B11: Hands-on Activity 1: Conduct a mock requirement gathering session for a fictional project.
B12: Documentation and traceability of requirements.
A13: 1.3 | B13: System Design
B14: Detailed exploration of the system design phase.
B15: Hands-on Activity 2: Create a system design document for a sample project.
B16: Architectural considerations and design principles.
A17: 2 | B17: Agile Principles and Communication | D17: Learners will explore Agile methodologies, focusing on its foundational values and principles. They will gain insights into Agile's core values, which prioritize individuals and interactions, working solutions, customer collaboration, and responding to change. Understanding these Agile principles is vital, as they introduce a flexible and customer-centric approach to software development, enabling teams to adapt to evolving requirements and deliver value efficiently. This knowledge equips learners with a modern, adaptable framework for software development, ensuring they can work effectively in dynamic environments and provide value to customers and stakeholders. | E17: 1
A18: 2.1 | B18: Agile Introduction and Values
B19: Introduction to Agile values
B20: Individuals and interactions, Working solutions
B21: Customer collaboration, Responding to change
B22: Agile principles (e.g., prioritizing customer needs, iterative development).
A23: 2.2 | B23: Scrum Framework
B24: Overview of Scrum framework
B25: Roles (Product Owner, Scrum Master, Development Team) and responsibilities.
B26: Scrum artifacts (Product Backlog, Sprint Backlog, Increment).
B27: Scrum ceremonies - Sprint Planning, Daily Standup, Sprint Review, Sprint Retrospective
B28: Hands-on Activity 3 - Conduct a mock Scrum Sprint with tasks, user stories, and a product backlog.
A29: 2.3 | B29: Kanban and Lean
B30: Understanding Kanban and Lean principles.
B31: Visualizing work with Kanban boards.
B32: Hands-on Activity 4 - Set up a Kanban board for a real-world scenario.
B33: Reducing waste in software development (Muda, Mura, Muri).
A34: 2.4 | B34: Scrum Simulation
B35: Form Scrum teams, assign roles, and simulate a Sprint with a focus on effective communication.
A36: 3 | B36: Agile Methodologies and Effective Communication | C36: Assignment 1: Agile Project Planning - Create a one-page project plan for a new software feature using Agile planning techniques. Include backlog items with estimated story points and a prioritized list of user stories. Assignment 2: Daily Standup Simulation - Write a script for a Daily Standup meeting for a development team working on the software feature from Assignment 1. Address a common challenge and incorporate a solution into the communication flow. Submission Guidelines: 1. Ensure that each answer is clear, concise, and reflects an understanding of the core concepts. 2. Diagrams can be hand-drawn and scanned or created using any digital drawing tool. 3. Provide references for any external sources used. Submit your work in a single PDF document by end of Module. | D36: Learners will dive into Agile Development methodology. They will learn how Agile teams plan and prioritize work, with a focus on backlog grooming and story point estimation. This knowledge is essential for learners, as it equips them with the skills needed to contribute to Agile teams effectively. They will be able to participate in Agile meetings, understand how work is organized, and understand the effort required for different tasks. This understanding ensures that they can collaborate seamlessly with their teams and contribute to the successful delivery of Agile projects. | E36: 0.5
A37: 3.1 | B37: Agile Planning and Estimation
B38: Agile planning techniques (backlog grooming, story points).
B39: Hands-on Activity 6: Plan and estimate a project using Agile methods.
B40: Creating and prioritizing user stories.
A41: 3.2 | B41: Daily Standup and Communication
B42: Conducting effective Daily Standup meetings.
B43: Common challenges and solutions in Daily Standup communication.
B44: Hands-on Activity 7: Participate in a Daily Standup meeting with a provided scenario.
A45: 3.3 | B45: Sprint Review and Stakeholder Communication
B46: The importance of Sprint Reviews in Agile.
B47: Preparing for and conducting a Sprint Review.
B48: Hands-on Activity 8: Plan and conduct a Sprint Review with stakeholders.

Sheet Programming & Algorithms
A1: Module | B1: Programming Constructs and Algorithms for Problem Solving
A2: Duration (Days) | B2: 2
A4: Sl. No. | B4: Topics
A5: 1 | B5: Programming as Problem solving activity
A6: 2 | B6: Developing a program – Structured way
A7: 3 | B7: Introduction to Pseudo Code
A8: 4 | B8: Sequence Construct
A9: 5 | B9: Selection Constructs
A10: 6 | B10: Iteration Constructs
A11: 7 | B11: Using all programming constructs
A12: 8 | B12: Dry Run
A13: 9 | B13: Developing a program – OO way
A14: 10 | B14: From Pseudo Code to Code

Sheet Linux, Shell Scripting and Git
A1: Module | B1: Linux Operating System and Source Code Management with Git
A2: Duration (Days) | B2: =SUM(E5:E109) -> 3
A4: Sl. No. | B4: Topics | C4: Day End Assignment Options | D4: Remarks | E4: Duration (Days)
A5: 1 | B5: Linux Basics and Command Line | C5: No Assignment | D5: Participants will learn about Linux's background, how to use the command line, manage files, and edit texts using tools like Nano and Vim. They'll also learn how to search inside files with grep and access a remote Linux System. Knowing these basics of Linux is important for learners, as it helps them work better and faster in software development and managing computer systems. These skills are the first step to becoming good at more advanced tech work. | E5: 0.75
A6: 1.1 | B6: Introduction to Linux
B7: Linux History and Philosophy
B8: Origins of Linux, GNU/Linux
B9: Open Source Movement
B10: Popular Linux Distributions
B11: Overview of Ubuntu, Fedora, CentOS
B12: Understanding Desktop Environments
B13: GNOME, KDE, XFCE
A14: 1.2 | B14: Command Line Basics
B15: Terminal Fundamentals
B16: Accessing the Terminal
B17: Basic Navigation Commands
B18: Directory Structures
B19: Home, Root, Bin, and Other Directories
B20: Absolute vs Relative Paths
B21: File Management Commands
B22: Creating, Listing, Deleting Files and Directories
A23: 1.3 | B23: Working with Files and Text Editors
B24: File Operations
B25: Copying, Moving, Removing Files
B26: Searching Within Files with grep
B27: Introduction to Nano and Vim
B28: Basic Operations: Opening, Editing, Saving Files
B29: Vim Modes and Navigation
A30: 1.4 | B30: Basic File System Structure and Permissions
B31: Exploring Linux File System Hierarchy
B32: Standard Directories and Their Roles
B33: File Permissions and Ownership
B34: Reading and Modifying File Permissions
B35: Changing File Ownership
A36: 1.5 | B36: Remote System Access
B37: Accessing remote system using SSH and Telnet access
B38: Copy Files from/to remote System
A39: 2 | B39: Source Code Management with Git | C39: Assignment 1: Initialize a new Git repository in a directory of your choice. Add a simple text file to the repository and make the first commit. Assignment 2: Branch Creation and Switching Create a new branch named 'feature' and switch to it. Make changes in the 'feature' branch and commit them. Assignment 3: Feature Branches and Hotfixes Create a 'hotfix' branch to fix an issue in the main code. Merge the 'hotfix' branch into 'main' ensuring that the issue is resolved. | D39: In this session on Source Code Management with Git, learners will understand why version control is crucial and how Git facilitates it. They will set up Git, learn to initialize repositories, and manage code changes. With hands-on practice, they'll master viewing commit history and reversing changes. The course will also cover branching, including creation, switching, and merging strategies. Advanced techniques such as managing complex merges and resolving conflicts will be taught. Learners will engage in collaborative Git workflows, including forking, cloning, and remote branch management. Finally, they'll hone skills in code review and collaboration through pull requests, essential for team-based projects. This knowledge is vital for maintaining code quality and efficient team collaboration. | E39: 0.75
A40: 2.1 | B40: Version Control with Git
B41: Git Introduction
B42: Why Version Control?
B43: Git Installation and Configuration
B44: Git Basics
B45: Initializing a Repository (git init)
B46: Staging and Committing Changes (git add, git commit)
A47: 2.2 | B47: Git Operations and Workflow
B48: Managing Changes
B49: Viewing Commit History (git log)
B50: Undoing Changes (git revert, git reset)
B51: Branching in Git
B52: Creating and Switching Branches (git branch, git checkout)
B53: Basic Merging Techniques
A54: 2.3 | B54: Branching and Merging
B55: Advanced Branching Strategies
B56: Feature Branching, Hotfix Branches
B57: Complex Merging Techniques
B58: Resolving Complex Merge Conflicts
B59: Rebase vs Merge
A60: 2.4 | B60: Collaborative Development with Git
B61: Collaborative Workflows in Git
B62: Forking and Cloning Repositories
B63: Managing Collaborative Changes
B64: Working with Branches Remotely
B65: Pushing and Pulling Branches
B66: Remote Branch Management
A67: 2.5 | B67: Code Review and Collaboration Practices
B68: Utilizing Pull Requests
B69: Creating and Managing Pull Requests
B70: Code Review Process
A71: 3 | B71: Shell Scripting with Bash | C71: Assignment 1: Ensure the script checks if a specific file (e.g., myfile.txt) exists in the current directory. If it exists, print "File exists", otherwise print "File not found". Assignment 2: Write a script that reads numbers from the user until they enter '0'. The script should also print whether each number is odd or even. Assignment 3: Create a function that takes a filename as an argument and prints the number of lines in the file. Call this function from your script with different filenames. Assignment 4: Write a script that creates a directory named TestDir and inside it, creates ten files named File1.txt, File2.txt, ... File10.txt. Each file should contain its filename as its content (e.g., File1.txt contains "File1.txt"). Assignment 5: Modify the script to handle errors, such as the directory already existing or lacking permissions to create files. Add a debugging mode that prints additional information when enabled. Assignment 6: Given a sample log file, write a script using grep to extract all lines containing "ERROR". Use awk to print the date, time, and error message of each extracted line. Data Processing with sed Assignment 7: Create a script that takes a text file and replaces all occurrences of "old_text" with "new_text". Use sed to perform this operation and output the result to a new file. Submission Guidelines: 1. Ensure that each answer is clear, concise, and reflects an understanding of the core concepts. 2. Diagrams can be hand-drawn and scanned or created using any digital drawing tool. 3. Provide references for any external sources used. Submit your work in a single PDF document by end of Module. | D71: In this session, you'll learn about Bash Shell Scripting and Text Processing in Linux, which are essential skills in the computer world today. Starting with basic Linux commands, you'll learn how to write scripts, manage files, and process data. This session is very practical for anyone using computers, especially for tasks like automating routine work, analyzing data, and managing systems. By the end of the session, you'll be able to handle complex tasks more easily and efficiently, saving time and effort. This training is especially valuable for those in IT, data analysis, and system administration, making their work smoother and more efficient. | E71: 1.5
A72: 3.1 | B72: Bash Scripting Basics
B73: Shell Scripting Basics
B74: Creating and Running Shell Scripts
B75: Script File Structure
B76: Making Scripts Executable
B77: Basic Shell Script Examples
B78: Variables and Data Types
B79: Environment Variables
B80: Custom Variables
B81: Data Types and Declaration
B82: Working with Strings and Numbers
A83: 3.2 | B83: Control Structures and Functions
B84: Control Structures
B85: Conditional Statements (if, then, else, elif)
B86: Loop Structures (for, while, until)
B87: Case Statements
B88: Functions in Bash
B89: Defining and Calling Functions
B90: Function Parameters and Return Values
B91: Scope of Variables in Functions
A92: 3.3 | B92: Advanced Scripting Techniques
B93: Advanced Bash Features
B94: Arrays and Associative Arrays
B95: Reading and Writing Files
B96: Redirecting Input and Output
B97: Using Pipes and Filters
B98: Error Handling
B99: Exit Status of Commands
B100: Trap Statements for Error Detection
B101: Debugging Bash Scripts
...

Sheet RDBMS and SQL
A1: Module | B1: RDBMS and SQL
A2: Duration (Days) | B2: =SUM(E5:E78) -> 3
A4: Sl. No. | B4: Topics | C4: Day End Assignment Options | D4: Remarks | E4: Duration (Days)
A5: 1 | B5: RDBMS Fundamentals | C5: Assignment 1: Analyze a given business scenario and create an ER diagram that includes entities, relationships, attributes, and cardinality. Ensure that the diagram reflects proper normalization up to the third normal form. Assignment 2: Design a database schema for a library system, including tables, fields, and constraints like NOT NULL, UNIQUE, and CHECK. Include primary and foreign keys to establish relationships between tables. Assignment 3: Explain the ACID properties of a transaction in your own words. Write SQL statements to simulate a transaction that includes locking and demonstrate different isolation levels to show concurrency control. Assignment 4: Write SQL statements to CREATE a new database and tables that reflect the library schema you designed earlier. Use ALTER statements to modify the table structures and DROP statements to remove a redundant table. Assignment 2: Demonstrate the creation of an index on a table and discuss how it improves query performance. Use a DROP INDEX statement to remove the index and analyze the impact on query execution. Assignment 6: Create a new database user with specific privileges using the CREATE USER and GRANT commands. Then, write a script to REVOKE certain privileges and DROP the user. Assignment 7: Prepare a series of SQL statements to INSERT new records into the library tables, UPDATE existing records with new information, and DELETE records based on specific criteria. Include BULK INSERT operations to load data from an external source. | D5: In the RDBMS Fundamentals section, learners will understand the basics of relational databases and why they are important in storing and managing data. They will learn about tables, rows, and fields, and how keys and indexes help in organizing data efficiently. The section will cover designing databases with ER models and normalization to avoid data repetition. Learners will also explore different database architectures, including single-user and multi-user systems, as well as centralized and distributed databases. They will get to know how RDBMS ensures data accuracy and consistency using ACID properties and how it manages multiple data transactions and security levels. | E5: 0.75
A6: 1.1 | B6: Introduction to RDBMS
B7: Definition and Concepts of RDBMS
B8: Importance of RDBMS in Modern Computing
B9: Characteristics of RDBMS
A10: 1.2 | B10: Database Design
B11: ER Models: Entities, Relationships, Attributes, and Cardinality
B12: Normal Forms and Normalization Process
B13: Logical and Physical Database Design
A14: 1.3 | B14: RDBMS Architectures
B15: Single-user vs Multi-user Systems
B16: Centralized vs Distributed Databases
B17: Client-Server Architecture
A18: 1.4 | B18: Key RDBMS Components
B19: Tables, Fields, Rows, and Columns
B20: Primary Keys, Foreign Keys, and Indexes
B21: Constraints: NOT NULL, UNIQUE, CHECK, DEFAULT
A22: 1.5 | B22: Data Integrity and Transactions
B23: ACID Properties
B24: Locking and Concurrency Control
B25: Isolation Levels
A26: 2 | B26: SQL Language | D26: In the SQL Language section, learners will dive into the syntax and structure of SQL, the standard language for interacting with relational databases. They will learn to create, alter, and delete database objects using DDL commands and manage data types and storage engines. The section will also cover how to control access to data with DCL by managing users and permissions. For DML, learners will practice adding, updating, and deleting records, and using bulk operations for large datasets. The focus will be on practical SQL use, helping learners to execute database operations effectively and understand the role of SQL in database management and data manipulation. | E26: 0.75
A27: 2.1 | B27: SQL Syntax and Statement Structure
B28: SQL Keywords and Identifiers
B29: Statement Clauses and Predicates
B30: Comments and Formatting Best Practices
A31: 2.2 | B31: DDL - Data Definition Language
B32: Database and Table Operations
B33: CREATE, ALTER, DROP for Databases and Tables
B34: CREATE INDEX and DROP INDEX
B35: Data Types and Table Storage Engines
A36: 2.3 | B36: DCL - Data Control Language
B37: User and Permission Management
B38: CREATE USER, DROP USER
B39: GRANT, REVOKE Permissions
B40: Roles and Privileges
A41: 2.4 | B41: DML - Data Manipulation Language
B42: Data Management
B43: INSERT, UPDATE, DELETE
B44: BULK INSERT and Data Import/Export Techniques
A45: 2.5 | B45: DQL - Data Query Language | C45: Assignment 1: Write a SELECT query to retrieve all columns from a 'customers' table, and modify it to return only the customer name and email address for customers in a specific city. Assignment 2: Craft a query using an INNER JOIN to combine 'orders' and 'customers' tables for customers in a specified region, and a LEFT JOIN to display all customers including those without orders. Assignment 3: Utilize a subquery to find customers who have placed orders above the average order value, and write a UNION query to combine two SELECT statements with the same number of columns. Assignment 4: Compose SQL statements to BEGIN a transaction, INSERT a new record into the 'orders' table, COMMIT the transaction, then UPDATE the 'products' table, and ROLLBACK the transaction. Assignment 5: Begin a transaction, perform a series of INSERTs into 'orders', setting a SAVEPOINT after each, rollback to the second SAVEPOINT, and COMMIT the overall transaction. Assignment 6: Draft a brief report on the use of transaction logs for data recovery and create a hypothetical scenario where a transaction log is instrumental in data recovery after an unexpected shutdown. | D45: Learners will will acquire the ability to retrieve and manage database information proficiently. They will learn to execute complex queries with SELECT, apply filters with WHERE, and organize results using ORDER BY and GROUP BY. Simultaneously, they'll gain expertise in ensuring data integrity through transaction control using BEGIN, COMMIT, ROLLBACK, and SAVEPOINT commands. This dual focus equips learners with the essential skills to both analyze data and maintain transactional consistency, vital for database reliability and performance in any business environment. | E45: 0.75
B46: Basic Data Retrieval
B47: SELECT Statements
B48: WHERE Clauses and Filtering Data
B49: ORDER BY, GROUP BY, and HAVING Clauses
B50: Advanced Data Retrieval
B51: JOIN Operations: INNER, LEFT, RIGHT, FULL, CROSS
B52: Subqueries and Correlated Subqueries
B53: UNION, INTERSECT, and EXCEPT Clauses
B54: Functions and Expressions
B55: Scalar Functions: Numeric, String, Date
B56: Aggregate Functions: COUNT, AVG, SUM, MIN, MAX
B57: CASE Expressions and Conditional Logic
A58: 2.6 | B58: TCL - Transaction Control Language
B59: Transaction Management
B60: Understanding Implicit and Explicit Transactions
B61: BEGIN TRANSACTION, COMMIT, ROLLBACK
B62: SAVEPOINT, RELEASE SAVEPOINT
B63: Transaction Log Management
A64: 2.7 | B64: Advanced SQL Concepts | D64: The Advanced SQL Concepts section will introduce learners to Window Functions, which are essential for performing complex calculations across sets of rows related to the current row. They'll learn how to use the OVER() clause, PARTITION BY, and ranking functions to create sophisticated data summaries. Additionally, they will explore performance tuning through indexing strategies and understand how to analyze and optimize query performance. Security practices, such as preventing SQL injection attacks and ensuring secure coding, will be emphasized, along with methods for data protection, including encryption and masking. These advanced skills are vital for optimizing database queries and safeguarding sensitive information. | E64: 0.75
B65: Window Functions
B66: OVER() Clause Basics
B67: Partitioning Data with PARTITION BY
B68: Ranking Functions: ROW_NUMBER(), RANK(), DENSE_RANK(), NTILE()
B69: Window Frames and Functions: LEAD(), LAG(), FIRST_VALUE(), LAST_VALUE()
B70: Cumulative and Moving Aggregates
B71: Performance Tuning and Optimization
B72: Indexing Strategies and Types
B73: Query Performance Analysis
B74: Execution Plans and Optimizer Hints
B75: Security and SQL Best Practices
B76: Avoiding SQL Injection Vulnerabilities
... B78: Database Encryption and Data Masking

Sheet TestingFundamentals
A1: Module | B1: Testing Fundamentals
A2: Duration (Days) | B2: =SUM(D5:D52) -> 3
A4: Sl. No. | B4: Topics | C4: Remarks | D4: Duration (Days)
A5: 1 | B5: Software Testing Fundamentals | C5: This module covers Software Testing Fundamentals, emphasizing its role in the Software Development Life Cycle (SDLC) and its goals and principles. Learners explore various levels of testing, including Unit Testing, Integration Testing, System Testing, and Acceptance Testing, understanding their objectives and environments. They delve into testing techniques like Static and Dynamic Testing, as well as White-box, Black-box, and Grey-box Testing. Types of testing, such as Functional and Non-Functional Testing, are discussed, along with test planning, design, execution, and defect management processes. Practical skills include creating test strategies, writing test cases, executing tests, and managing defects, ensuring comprehensive software quality assurance. | D5: 1
A6: 1.1 | B6: Overview of Software Testing
B7: Definition and importance of software testing in the SDLC
B8: Goals and principles of software testing
A9: 1.2 | B9: Levels of Software Testing
B10: Introduction to Unit Testing, Integration Testing, System Testing, and Acceptance Testing
B11: Understanding the objectives, target, and environment of each level
A12: 1.3 | B12: Software Testing Techniques
B13: Static vs. Dynamic Testing Techniques
B14: White-box, Black-box, and Grey-box Testing
A15: 1.4 | B15: Types of Testing
B16: Functional Testing: Including regression, smoke, sanity, and user acceptance testing
B17: Non-Functional Testing: Including performance, load, stress, usability, and security testing
A18: 1.5 | B18: Test Planning
B19: Creating test strategies and test plans
B20: Resource and environment planning
A21: 1.6 | B21: Test Design
B22: Writing test cases and test scripts
B23: Designing tests based on requirements and specifications
A24: 1.7 | B24: Test Execution
B25: Executing test cases and recording results
B26: Managing test cycles
A27: 1.8 | B27: Defect Management
B28: Defect lifecycle management
B29: Reporting and tracking defects using tools
A30: 2 | B30: Introduction to JIRA | C30: This module provides an Introduction to Jira, elucidating its significance in project management and issue tracking. Learners navigate the Jira interface, mastering its core features. They delve into Project Configuration, customizing settings, understanding roles, and permissions. Workflow Management is explored, encompassing defining workflows, customizing them, and aligning with team processes. Practical skills include creating and configuring projects, managing project categories and versions, and handling user and role management. Learners also learn to create and manage issues of various types, track progress, and work with subtasks for detailed tracking and task breakdown. This foundational knowledge equips learners for effective utilization of Jira in project management contexts. | D30: 1
A31: 2.1 | B31: Introduction to Jira
B32: Understanding what Jira is and its role in project management and issue tracking
B33: Navigating the Jira interface and its core features
A34: 2.2 | B34: Project Configuration
B35: Setting up a project in Jira, customizing project settings
B36: Understanding project roles and permissions
A37: 2.3 | B37: Workflow Management
B38: Defining workflows, status, and transitions
B39: Customizing workflows to match team processes
A40: 2.4 | B40: Creating Projects
B41: Creating and configuring project types (Scrum, Kanban, etc.)
B42: Managing project categories and versions
A43: 2.5 | B43: User and Role Management
B44: Adding users to Jira
B45: Assigning users to roles and managing access
A46: 2.6 | B46: Creating and Managing Issues
B47: Creating different types of issues (Stories, Tasks, Bugs)
B48: Editing and tracking issue progress
A49: 2.7 | B49: Working with Subtasks
B50: Breaking down issues into subtasks for detailed tracking
B51: Managing subtask assignments and statuses
A52: 3 | B52: Mini-Projects | D52: 1
A53: 3.1 | B53: Mini-Project 1: E-Commerce Website Functional Testing
B54: Duration: 2 hours
B55: Objective: To validate the functional requirements of an e-commerce website's checkout process.
B56: Tasks:
B57: Review the requirement documentation for the checkout process.
B58: Write test cases for a complete checkout flow, including adding items to the cart, applying discounts, and processing payment.
B59: Perform a smoke test on the key features of the checkout process.
B60: Log test results and report any defects found using a tool like JIRA.
B61: Tag the reported issues appropriately and assign them to the developer role in JIRA.
A62: 3.2 | B62: Mini-Project 2: Performance Testing on a Landing Page
B63: Duration: 2 hours
B64: Objective: To assess the performance of an e-commerce website's landing page under load.
B65: Tasks:
B66: Create a simple performance test plan outlining the objectives, such as page load time under X number of users.
B67: Use a free or trial version of a performance testing tool to simulate multiple users accessing the landing page simultaneously.
B68: Record the performance data and analyze it against the performance objectives.
B69: Document any performance issues in JIRA, including relevant screenshots and data from the performance testing tool.

Sheet Core Java
A1: Module | B1: Core Java Programming
A2: Duration (Days) | B2: =SUM(D5:D168) -> 10
G3: Project Based Learning Scenario
A4: Sl. No. | B4: Topics | C4: Remarks | D4: Duration (Days) | G4: Assignment 1 | H4: Assignment 2
A5: 1 | B5: Java Fundamentals | C5: Learner will understand the essentials of setting up a Java development environment and the syntax required to write Java programs. They'll learn to configure tools like JDK and IDEs, which are vital for code development and execution. The engineer will also delve into the core principles of object-oriented programming, understanding classes, objects, and inheritance, which are fundamental in crafting structured and maintainable code. Additionally, they will acquire skills in managing code execution flow and error handling through control statements and exception handling, crucial for building robust applications. | D5: 2 | G5: Development Scenario: Insurance Claim Processing Terminal (ICPT) Day 1: Java Fundamentals and Environment Setup Objective: Set up a development environment and start building the core classes of the application. Tasks: Install JDK and configure Eclipse or IntelliJ IDEA., Create basic classes such as Claim, PolicyHolder, and InsurancePolicy. Implement control flow to handle claim processing steps: Create Claim, Validate Claim, Process Claim, and Reject/Approve Claim. Day 2: OOP, Collections, and Exception Handling Objective: Structure the application using object-oriented principles and implement exception handling. Tasks: Design the application to use collections for managing claims and policyholders. Implement custom exceptions to handle possible scenarios in claim processing like ClaimValidationException. Refine the application to handle collections of different types of insurance policies using Java Generics. Day 3: Multithreading and Advanced Java Features Objective: Introduce multithreading for handling multiple claims simultaneously and utilize advanced features for better structure. Tasks: Implement multithreading to process claims in parallel, simulating a real-life environment where multiple claims are processed at once. Use concurrency utilities to manage threads and ensure thread safety when accessing shared resources. Integrate Java Streams for filtering and summarizing claim data. Use bounded type parameters and wildcards to create a flexible system that can handle different types of insurance claims. Day 4: I/O, Networking, and JDBC Objective: Enable file-based persistence, network communication, and database integration for the claim processing. Tasks: Implement serialization to save and load claims and policyholder information to and from the file system. Transition the application to a simple client-server model over the network to handle claim submissions. Use JDBC to connect to an RDBMS for storing and retrieving claims and related data persistently. Implement the Java 8 Date and Time API to manage claim submission dates and deadlines. Day 5: Debugging, Performance, and Design Patterns Objective: Debug the system, enhance performance, and implement design patterns for clean architecture. Tasks: Debug the application using IDE features, set breakpoints, and inspect variables. Profile the application to detect memory leaks and analyze performance. Day 6: Unit Test the Application Objective: Unit Test your application Tasks: Write JUnit tests for each module, focusing on the claim validation logic and policyholder management. Day 7: Design Patterns Objective: Adopt Design patterns for better code quality Tasks: Introduce the Factory Method design pattern to create different types of claims based on the insurance policy. Use the Adapter design pattern to integrate with external systems for claim verification. Apply the Strategy pattern to encapsulate different claim processing algorithms. Use the Command pattern to represent claim processing operations that can be queued, executed, or undone. Submission Guidelines: 1. Ensure that each answer is clear, concise, and reflects an understanding of the core concepts. 2. Diagrams can be hand-drawn and scanned or created using any digital drawing tool. 3. Provide references for any external sources used. Submit your work in a single PDF document by end of Module. 4. You must submit your code on gitlab by the end of next day | H5: Development Scenario: Retail Banking Application (RBA) Day 1: Java Fundamentals and Environment Setup Objective: Establish the development environment and create fundamental classes. Tasks: Install the JDK and set up an IDE (Eclipse or IntelliJ IDEA). Create primary classes such as Account, Customer, and Transaction with basic attributes. Day 2: OOP, Collections, and Exception Handling Objective: Implement core object-oriented principles and manage application data. Tasks: Design a Bank class to manage Customer and Account objects using collections (e.g., HashMap for account management). Create custom exceptions (e.g., InsufficientFundsException) for handling common banking errors. Day 3: Multithreading and Advanced Java Features Objective: Introduce concurrent transactions and employ advanced features. Tasks: Implement a TransactionProcessor class that can handle multiple transactions concurrently using threads. Utilize Java 8 features such as Streams and Lambdas to filter and summarize transaction data. Day 4: I/O, Networking, and JDBC Objective: Add persistent storage and networking capability for transaction processing. Tasks: Implement functionality to read and write customer data to files using I/O streams. Establish a JDBC connection to a database to store and retrieve transaction records. Day 5: Debugging, Performance, and Design Patterns Objective: Enhance application performance and incorporate design patterns. Tasks: Profile the application using tools like VisualVM to identify and fix performance issues. Apply the Singleton pattern to ensure only one instance of the Bank class is used throughout the application. Day 6: Unit Test the Application Objective: Ensure the correctness of the application through unit testing. Tasks: Write JUnit tests for the Account and Customer classes to validate the business logic. Create unit tests for the TransactionProcessor to ensure it handles concurrent transactions properly. Day 7: Design Patterns Objective: Implement additional design patterns to refine the application architecture. Tasks: Use the Factory pattern to create different types of accounts (e.g., Checking, Savings, Business). Implement the Observer pattern to notify customers via email or SMS when transactions are processed on their accounts. Submission Guidelines: 1. Ensure that each answer is clear, concise, and reflects an understanding of the core concepts. 2. Diagrams can be hand-drawn and scanned or created using any digital drawing tool. 3. Provide references for any external sources used. Submit your work in a single PDF document by end of Module. 4. You must submit your code on gitlab by the end of next day
A6: 1.1 | B6: Java Environment Setup
B7: Installing JDK
B8: Configuring IDEs (Eclipse, IntelliJ IDEA)
A9: 1.2 | B9: Java Syntax and Basic Constructs
B10: Primitive Data Types and Variables
B11: Operators and their Precedence
B12: Control Flow Statements (if, switch, loops - for, while, do-while)
A13: 2 | B13: Java Object-Oriented Programming (OOP) Basics
A14: 2.1 | B14: Object-Oriented Programming (OOP)
B15: Classes and Objects: Definitions and Differences
B16: Constructors: Purpose and Types
B17: Encapsulation: Access Modifiers and Getters/Setters
B18: Inheritance: Superclass and Subclass Relationships
B19: Polymorphism: Method Overloading and Overriding
A20: 2.2 | B20: Organizing Code
B21: Packages: Creating and Using Packages
B22: Classpath: Understanding and Setting the Classpath
B23: Java Modules: Modular Programming in Java
A24: 3 | B24: Exception Handling
A25: 3.1 | B25: Exception Handling
B26: try-catch Blocks: Basic Exception Handling
B27: Creating Custom Exceptions: When and How to Create
A28: 4 | B28: Java Collections Framework and Generics | C28: Learner will learn to efficiently manage data in Java using the Collections Framework, mastering arrays, lists, sets, maps, and their respective interfaces and implementations. They will also understand generics for type-safe operations. Proficiency in iterators and comparators for collection traversal and sorting is covered. Additionally, skills in string manipulation through various String class methods and the performance benefits of StringBuilder and StringBuffer are emphasized. | D28: 1.5
A29: 4.1 | B29: Arrays: Declaration, Initialization, and Usage
B30: Introduction to List interface.
B31: Exploring ArrayList and LinkedList.
A32: 4.2 | B32: Understanding the Set interface.
B33: Working with HashSet, LinkedHashSet, and TreeSet.
B34: Differentiating between various Set implementations.
A35: 4.3 | B35: Introduction to Map interface.
B36: Exploring HashMap, LinkedHashMap, and TreeMap.
B37: Key-value pair management and use cases.
A38: 4.4 | B38: Iterators and Comparators
A39: 5 | B39: String Handling
A40: 5.1 | B40: String Manipulation: Methods in the String Class
B41: StringBuilder and StringBuffer: Mutability and Performance
A42: 6 | B42: Concurrency and Multithreading in Java | C42: Learner will acquire skills to create, manage, and synchronize threads, crucial for building efficient, high-performance applications. They'll understand thread lifecycles, coordination, and advanced utilities like executors, ensuring robust thread safety. These competencies are vital for developing complex, responsive software that fully utilizes system capabilities. | D42: 0.5
A43: 6.1 | B43: Multithreading Basics: Creating and Managing Threads
A44: 6.2 | B44: Thread Lifecycle: States and Transitions
A45: 6.3 | B45: Synchronization and Inter-thread Communication
B46: Thread Synchronization: Synchronized Blocks and Methods
A47: 6.4 | B47: Thread Pools and Concurrency Utilities
B48: Concurrency Utilities: Executors, Concurrent Collections, CompletableFuture
A49: 6.5 | B49: Thread Safety: Writing Thread-Safe Code, Immutable Objects
A50: 7 | B50: Advanced Java Features | C50: Learners will explore generics for type-safe code and learn to use generic classes, methods, and collections to create flexible and reusable code components. They'll delve into Java's reflection API to interact with and modify runtime classes, and annotations to provide metadata within code. They will be introduced to lambda expressions and functional programming concepts, enabling more concise and expressive code. Understanding functional interfaces and method references will further streamline their code, promoting a functional approach to solving problems and manipulating data. These advanced skills are essential for writing clean, maintainable, and efficient Java code. | D50: 1
A51: 7.1 | B51: Generics and Type Safety
B52: Generic Classes and Methods
B53: Bounded Type Parameters and Wildcards
B54: Generic Collections and Type Inference
A55: 7.2 | B55: Java Reflection and Annotations
B56: Reflection API: Accessing and Modifying Runtime Classes
B57: Annotations: Built-in and Custom Annotations
A58: 7.3 | B58: Lambda Expressions and Functional Programming
B59: Functional Programming Concepts
B60: Lambda Expressions: Syntax and Usage
B61: Functional Interfaces: Predicate, Function, Consumer, Supplier
B62: Method References
A63: 8 | B63: Java IO, NIO, and Networking | C63: Learning Java IO and NIO is essential for handling files and directories, enabling learners to read, write, and manage data on a storage medium. Advanced IO covers streams and file operations, while NIO introduces channels and buffers for more efficient data handling. Networking teaches the creation of networked applications using sockets and protocols. The Java Date and Time API provides a comprehensive framework for managing dates, times, and time zones, crucial for applications that require time-sensitive operations. These capabilities are foundational for developing a wide range of Java applications, from desktop to server-side programming. | D63: 1
A64: 8.1 | B64: Java IO Basics
B65: File Handling (FileReader, FileWriter)
B66: BufferedReader, BufferedWriter
A67: 8.2 | B67: Advanced Java IO
B68: Streams and File I/O
B69: Serialization and Deserialization
A70: 8.3 | B70: New IO (NIO)
B71: Channels, Buffers, Selectors
A72: 8.4 | B72: File and Directory Operations
A73: 8.5 | B73: Java Networking
B74: Sockets, URL, InetAddress
B75: Building Client-Server Applications
A76: 9 | B76: Java 8 Date and Time API
A77: 9.1 | B77: Working with LocalDate, LocalTime, LocalDateTime
A78: 9.2 | B78: Temporal Adjusters, Periods, and Time Zones
A79: 10 | B79: JDBC Programming | C79: Learner will gain an understanding of JDBC programming, They'll explore JDBC to connect Java applications to a database, execute queries, and handle results. Advanced JDBC techniques such as using PreparedStatements and CallableStatements improve query efficiency and enable transaction management, while handling database metadata allows for dynamic database interaction, all critical skills for backend development in Java. | D79: 1
A80: 10.1 | B80: Basics of JDBC
B81: JDBC overview and architecture
B82: Establishing database connections
B83: Executing SQL queries using JDBC
B84: Processing query results with ResultSet
A85: 10.2 | B85: Advanced JDBC
B86: Using PreparedStatement for efficient queries
B87: Handling database metadata
B88: Executing stored procedures with CallableStatement
B89: Transaction management in JDBC
A90: 11 | B90: Java Testing and Debugging | C90: Java Testing and Debugging are crucial skills for Learners to ensure the quality and reliability of their Java applications. Learning JUnit provides a framework for unit testing, enabling the creation of test cases with annotations like @Test and assertion methods like assertEquals. Debugging techniques involve using IDE features like breakpoints, variable inspection, and call stack analysis to identify and fix issues efficiently. Engineers also explore logging frameworks like Log4j and performance analysis tools like VisualVM and JProfiler to optimize code for memory usage, CPU performance, and garbage collection efficiency, contributing to the creation of robust and high-performing Java applications. | D90: 1
A91: 11.1 | B91: JUnit Framework
B92: Basics of JUnit for unit testing
B93: Annotations: @Test, @Before, @After, @BeforeClass, @AfterClass
B94: Writing test cases and assertions: assertEquals, assertTrue, assertFalse
B95: Organizing tests into suites
A96: 11.2 | B96: Debugging Techniques
B97: Using IDE debugging features (Eclipse, IntelliJ)
B98: Setting and using breakpoints
B99: Inspecting variables and expressions
B100: Analyzing call stacks
...

Sheet Selenium&API Testing
A1: Module | B1: Selenium
A2: Duration (Days) | B2: =SUM(E5:E146) -> 10
A4: Sl. No. | B4: Topics | C4: Day End Assignment Options | D4: Remarks | E4: Duration (Days)
A5: 1 | B5: Testing with Selenium | C5: Task 1: Eclipse IDE Basic Operations Topic: Navigating the Eclipse Interface Description: Demonstrate the basic operations in Eclipse by running a pre-written Java program, observing the console output, and then stopping the execution. Steps: Open Eclipse IDE and select the workspace that contains the pre-written Java program. Locate the Java program in the Package Explorer and open it in the editor. Click on the 'Run' button to start the program and observe the output in the Console window. Use the 'Stop' button to terminate the program execution. Describe what the 'Pause' button does in the context of running programs. Task 2: Debugging with Eclipse Topic: Error Handling and Debugging Description: Utilize Eclipse's debugging features to identify and fix a simple logical error in a Java program. Steps: Open the provided Java program with a known logical error in Eclipse. Start the debugger by clicking on the 'Debug' button. Use breakpoints to pause the execution at critical points in the program. Step through the code using 'Step into' and 'Step over' to observe variable values. Identify the logical error based on variable values and code flow. Correct the error and rerun the program to ensure it's fixed. Task 3: Writing and Running a Simple Selenium Test Topic: First Test Case and WebDriver Basics Description: Write a simple Selenium WebDriver test in Eclipse to open a web browser and navigate to a specified URL. Steps: Open Eclipse and create a new Java Project dedicated to Selenium tests. Within the project, set up the Selenium WebDriver by adding the WebDriver JAR files to the build path. Create a new Java class file for the test case. Write a Java method using WebDriver to initiate a Firefox, Chrome, or Safari browser session. Use WebDriver to navigate to 'http://example.com' or a similar simple web page. Run the test to ensure the browser opens and navigates to the URL successfully. | D5: This course offers comprehensive training in Testing with Selenium, beginning with an Introduction to Eclipse IDE. Learners master Eclipse's interface, basic operations, and debugging techniques. They set up Eclipse for Selenium, configuring Java and Selenium WebDriver, and structuring projects. In the Selenium section, learners create their first test cases, delve into WebDriver's architecture, and explore advanced navigation and WebElement interaction. Advanced topics cover effective element selection, synchronization strategies, handling alerts and multiple windows, and complex user interactions. Practical skills include navigating complex UI components, such as Ajax elements, calendars, and Shadow DOM. By course end, learners are proficient in Selenium testing, equipped to automate web testing tasks efficiently. | E5: 1
A6: 1.1 | B6: Introduction to Eclipse IDE
B7: Getting Started with Eclipse
B8: Navigating the Eclipse Interface
B9: Basic Operations: Run, Stop, Pause
B10: Debugging Techniques: Breakpoints, Console Output, Watch Variables
B11: Error Handling and Debugging
B12: Analyzing Errors through the Problem Window
B13: Debugging with 'Step into' and 'Step over'
A14: 1.2 | B14: Setting Up Eclipse for Selenium
B15: Java and Selenium Configuration
B16: Installing Java in Eclipse
B17: Setting Up WebDriver Java Client
B18: Project Creation and Package Structuring
B19: First Test Case and WebDriver Basics
B20: Creating a First Java Test Case
B21: Importing WebDriver Source Files
B22: Understanding WebDriver's Architecture
A23: 1.3 | B23: Mastering WebDriver
B24: WebDriver Deep Dive
B25: WebDriver Interface and Its Methods
B26: WebElement Interface and Its Use Cases
B27: Launching Browsers: Firefox, Chrome, Safari
A28: 1.4 | B28: Browser and Navigation Commands | C28: Task 1: Page Title Verification Topic: Page Interaction Commands Description: Write a simple Selenium script to open a specified URL and verify the title of the page. Steps: Launch Eclipse IDE and create a new Java class in the Selenium project. In the main method, instantiate the WebDriver and navigate to 'http://example.com'. Use driver.getTitle() to retrieve the page title and store it in a variable. Assert that the page title matches the expected title using a simple if statement that prints out the verification result. Close the browser using driver.quit(). Task 2: Element Interaction and State Verification Topic: WebElements Commands and Identification Description: Write a Selenium script to interact with an input field on a form, enter text, and verify the text was entered correctly. Steps: Open the same Java class used in Task 1. Navigate to a web page with an input field (e.g., a search box). Use driver.findElement() to locate the input field by its name or ID. Enter text using the sendKeys() method and clear it with clear(). Retrieve the input field value and verify it matches the text entered. Verify the input field is displayed and enabled by using isDisplayed() and isEnabled(). Task 3: Locator Strategy Implementation Topic: Locator Techniques and Effective Element Selection Description: Craft CSS Selector and XPath locators for an element on a web page and demonstrate the selection in a Selenium script. Steps: Use the Eclipse IDE to open the existing Selenium project. Open a web page that has a uniquely identifiable element (like a button with an ID). Write two separate locators in the Selenium script: one using CSS Selector and one using XPath. Use driver.findElement() to find the element using both locators separately, printing out a confirmation that the element has been found. Discuss the difference between absolute and relative XPath expressions and when to use each. | E28: 1
B29: Page Interaction Commands
B30: Opening a URL and Verifying Page Titles
B31: Retrieving Page Source and Understanding Its Structure
B32: The Difference between Close and Quit
B33: Advanced Navigation
B34: Navigating Back and Forward
B35: Refreshing Pages and Navigating to a Specific Page
A36: 1.5 | B36: WebElements Commands and Identification
B37: Interacting with WebElements
B38: Identifying Elements: findElement vs. findElements
B39: Entering and Clearing Text from Input Fields
B40: Click Actions on Different WebElements
B41: WebElement State Verification
B42: Checking Element Presence, Display Status, and Enabled State
A43: 1.6 | B43: Locator Techniques and Effective Element Selection
B44: Locator Fundamentals
B45: Understanding HTML Locators
B46: CSS Selectors and XPath
B47: Effective Locators
B48: Creating Effective Absolute and Relative XPath Expressions
B49: Utilizing Tools for Locator Strategy | C49: Task 1: Form Element Interaction and Data Extraction Topic: Advanced Element Interaction - Handling Tables and Form Elements Description: Write a Selenium script to extract data from a table and interact with form elements like checkboxes and radio buttons on a sample web page. Steps: Launch the web browser and navigate to a predefined web page with a table and form elements. Use Selenium's WebDriver to locate the table element and retrieve the text from a specific cell. Locate a checkbox and a radio button on the form and use Selenium commands to select and unselect the checkbox, and select the radio button. Print out the extracted data and the status of checkbox and radio button selections to the console. Task 2: Synchronization and Alert Handling Topic: Selenium Synchronization Strategies and Handling Alerts Description: Implement an explicit wait to synchronize a web element's presence and handle a simple JavaScript alert on the page. Steps: Open a web browser and navigate to a predefined web page that triggers a JavaScript alert after a button click. Implement an explicit wait using WebDriverWait to wait for the button to become clickable. Click the button to trigger the alert and then implement another explicit wait to ensure the alert is present. Use Selenium's Alert interface to accept the alert and then print a confirmation to the console.
A50: 1.7 | B50: Advanced Element Interaction | E50: 2
B51: Handling Tables and Form Elements
B52: Extracting Data from Tables, Checkboxes, and Radio Buttons
B53: Dropdown Interaction with Selenium's Select Class
A54: 1.8 | B54: Selenium Synchronization Strategies
B55: Implementing Waits
B56: Implicit vs. Explicit Waits
B57: Fluent Waits and Polling with WebDriverWait
B58: Handling Alerts and Multiple Windows
B59: Managing Simple, Confirmation, and Prompt Alerts
B60: Switching between Window Handles and Frames
A61: 1.9 | B61: User Interactions and Complex Scenarios
B62: The Actions Class
B63: Mouse Movements, Drag-and-Drop, and Context Clicks with the Actions Class
B64: Complex UI Components
B65: Handling Ajax Components, Calendars, and Infinite Scrolling
B66: Working with Complex Elements like Shadow DOM and SVG
A67: 2 | B67: TestNG Framework | C67: Task 1: Create a Simple TestNG Class with Basic Annotations Topic: Annotation and Execution with TestNG Description: Create a basic TestNG class that demonstrates the use of fundamental annotations. This class will include two test methods: one that passes and one that intentionally fails to illustrate the assertion mechanism. Steps: Open your IDE and create a new Java class within your test project. Import the TestNG library and set up the class with the @Test annotation. Write the first test method testPass() that asserts a true condition, like Assert.assertTrue(1 == 1);. Write the second test method testFail() that asserts a false condition, like Assert.assertTrue(1 == 2);. Annotate both methods with @Test and give them meaningful names, such as shouldPass and shouldFail. Execute the TestNG class using the IDE’s TestNG plugin or via command line, and observe the output. Briefly describe what the @BeforeMethod and @AfterMethod annotations do, and how they can be utilized in setting up and tearing down test conditions. | D67: This comprehensive course covers TestNG Framework essentials, starting with an Introduction to TestNG, emphasizing its benefits, features, and setup. Learners explore TestNG annotations, running test suites, and advanced techniques like grouping, dependency management, and generating reports. Practical skills include assertions, parameterization, multi-browser, and parallel testing. The course then delves into Automation Frameworks, discussing their essence, features, and benefits, focusing on data-driven and hybrid frameworks. Learners also master the Page Object Model design pattern with OOP concepts. Additionally, Maven Life Cycle and Command Line Mastery are covered, including commands, life cycle phases, JAR generation, and deployment using Maven Nexus and the Maven Deploy Plugin. By the course end, learners are proficient in TestNG and Maven, equipped for efficient test automation and deployment. | E67: 1
A68: 2.1 | B68: Introduction to TestNG
B69: Understanding TestNG
B70: Benefits and Features
B71: Downloading and Setting Up TestNG
A72: 2.2 | B72: Annotation and Execution with TestNG
B73: Annotations in TestNG
B74: Running Test Suites
A75: 2.3 | B75: Advanced TestNG Techniques
B76: Grouping and Dependency in Tests
B77: Test Case Sequencing
B78: Reports Generation in TestNG
B79: Assertions and Parameterization in TestNG
B80: Multi-Browser and Parallel Testing
A81: 3 | B81: Automation Framework | C81: Task 1: Execute Maven Commands to Compile and Run Tests Topic: Maven Life Cycle Description: Use Maven to compile a simple Java project and run its tests. This exercise will test the fresher's ability to interact with Maven, which is commonly used for building and managing any Java-based project. Steps: Open the command line or terminal. Navigate to the directory of a pre-existing simple Java project (this could be provided as a ZIP file for the purpose of the interview task). Execute mvn compile to compile the Java source files of the project. Next, run mvn test to execute the tests in the project. Describe what the mvn package command does and when you would use it. Task 2: Write a Simple Feature File with a Scenario Topic: Crafting Feature Files and Defining Scenarios Description: Create a basic feature file using Gherkin syntax for a login functionality of a web application, defining one scenario that includes a given, when, and then steps. Steps: Open your text editor or IDE with Cucumber support. Create a new file named login.feature. Define the Feature at the top of the file: Feature: User Login. Write a Scenario with the title: Scenario: Successful login with valid credentials. Use Gherkin syntax to define the steps: Given: "Given the user is on the login page". When: "When the user enters valid username and password". Then: "Then the user should be redirected to the dashboard". Save the feature file. | E81: 2
A82: 3.1 | B82: Understanding Automation Frameworks
B83: The Essence of Automation Frameworks
B84: Features and Benefits
B85: Data-Driven and Hybrid Frameworks
B86: Page Object Model Design Pattern with OOP Concepts
A87: 3.2 | B87: Maven Life Cycle
B88: Maven Command Line Mastery
B89: Maven Commands
B90: Maven Life Cycle: Create, Compile, Run Tests, Package, Install, Deploy
B91: Building JARs and FAT JAR Generation
B92: Deployment using Maven Nexus and the Maven Deploy Plugin
A93: 4 | B93: BDD – Behaviour Driven Development with Cucumber
A94: 4.1 | B94: Foundations of BDD
B95: Introduction to BDD
B96: The 'Three Amigos' Collaboration
B97: Cucumber and Gherkin Language Essentials
B98: Crafting Feature Files and Defining Scenarios
B99: Step Definitions and Cucumber Hooks
A100: 4.2 | B100: Best Practices and Configuration
B101: Effective Gherkin Writing Techniques
...

Sheet Docker
A1: Module | B1: Container Virtualization with Docker
A2: Duration (Days) | B2: =SUM(E5:E40) -> 1
A4: Sl. No. | B4: Topics | C4: Day End Assignment Options | D4: Remarks | E4: Duration (Days)
A5: 1 | B5: Docker Essentials | C5: Task 1: Run and Inspect a Docker Container Topic: Basic Docker Operations and Container Lifecycle Management Description: Use Docker CLI to run a container from an existing image and inspect its details. Steps: Open the terminal on your system. Pull a simple Docker image like hello-world or nginx using docker pull. Run the container using docker run command. List all running containers using docker ps. Inspect the running container by using docker inspect followed by the container ID or name to retrieve its metadata. Task 2: Tag and Push an Image to Docker Hub Topic: Docker Images and Registry Operations Description: Tag a local Docker image with a version and push it to Docker Hub (assuming the fresher has a Docker Hub account). Steps: Open the terminal on your system. List the available Docker images using docker images. Choose an image and tag it using docker tag with a new tag name, following the format: username/repository:tag. Log in to Docker Hub using docker login. Push the tagged image to Docker Hub using docker push. | D5: Learners grasp Docker Essentials, understanding its architecture and components, including Docker Engine, Images, Containers, and Docker Hub. They install Docker across various Linux distributions and execute basic operations like container running, listing, stopping, and removal. Container lifecycle management, networking, and persistent storage are covered, alongside advanced topics like health checks, resource limits, and Dockerfile crafting. Learners master Docker image building, tagging, and versioning, along with registry operations including pushing and pulling images. Security practices encompass container and image security, TLS configuration for Docker daemon access, and Docker security profiles like AppArmor, SELinux, and Seccomp. This knowledge empowers learners to efficiently deploy, manage, and secure Docker-based applications, crucial in modern DevOps and cloud environments. | E5: 1
A6: 1.1 | B6: Docker Architecture and Components
B7: Overview of Docker Engine, Docker Images, Containers, and Docker Hub
B8: Explanation of the Docker client-server architecture
A9: 1.2 | B9: Installation and Setup of Docker
B10: Step-by-step installation guide for various Linux distributions
B11: Post-installation steps to manage Docker as a non-root user
A12: 1.3 | B12: Basic Docker Operations
B13: Running containers: docker run
B14: Listing running containers: docker ps
B15: Stopping and removing containers: docker stop, docker rm
A16: 2 | B16: Docker Container Management
A17: 2.1 | B17: Container Lifecycle Management
B18: Detailed command usage for starting, stopping, inspecting, and logging containers
B19: Executing commands in running containers: docker exec
A20: 2.2 | B20: Docker Networking and Storage
B21: Overview of Docker's built-in network drivers (bridge, host, overlay)
B22: Setting up and managing persistent data with volumes: docker volume create
A23: 2.3 | B23: Advanced Container Management
B24: Implementing health checks in Dockerfiles
B25: Managing container resource limits: CPU and memory
A26: 3 | B26: Docker Images and Registry
A27: 3.1 | B27: Building and Managing Docker Images
B28: Crafting efficient Dockerfiles
B29: Building images: docker build
B30: Image tagging and versioning: docker tag
A31: 3.2 | B31: Docker Registry Operations
B32: Pushing and pulling images: docker push, docker pull
B33: Working with public and private registries (Docker Hub, Quay.io)
A34: 4 | B34: Docker Security Practices
A35: 4.1 | B35: Securing Docker Containers and Images
B36: Best practices for writing secure Dockerfiles
B37: Scanning images for vulnerabilities: Using Docker Hub and third-party tools
A38: 4.2 | B38: Docker Daemon Security
B39: Configuring TLS for secure Docker daemon access
B40: Docker security profiles: AppArmor, SELinux, and Seccomp

Sheet Ansible
A1: Module | B1: Configuration Automation with Ansible
A2: Duration (Days) | B2: =SUM(E5:E42) -> 1.5
A4: Sl. No. | B4: Topics | C4: Day End Assignment Options | D4: Remarks | E4: Duration (Days)
A5: 1 | B5: Introduction to Ansible | C5: Task 1: Write and Execute a Simple Ansible Playbook Topic: Ansible Playbooks - Writing Your First Playbook Description: Create a basic Ansible playbook that pings all hosts in the default inventory. Steps: Create a new file named ping.yml in your Ansible working directory. Write a playbook with a single task to use the ping module. Run the playbook using the command ansible-playbook ping.yml. Verify that you receive a pong response from all hosts listed in the /etc/ansible/hosts file. Task 2: Encrypt a String with Ansible Vault Topic: Ansible Vault - Securing Sensitive Data Description: Use Ansible Vault to encrypt a string and demonstrate how it can be used within a playbook. Steps: Open the terminal in your Ansible control machine. Use the Ansible Vault command to encrypt a string: ansible-vault encrypt_string 'my_secret_password' --name 'password'. Copy the output to a new playbook or an existing playbook variable section. Use the encrypted string in the playbook as a variable for demonstration. | D5: This module offers an Introduction to Ansible, detailing its role as a versatile automation tool for configuration management, application deployment, and task automation. Learners gain insight into its agentless architecture, playbooks, and inventory files, contrasting it with other tools like Puppet, Chef, and SaltStack. They set up Ansible across various Linux distributions, mastering playbook creation, variables, and task control. Learners delve into server configuration, application deployment, and advanced features like roles, Ansible Vault for securing sensitive data, and dynamic inventory for cloud providers. They also explore Ansible's application in network automation, cloud resource management, and orchestrating Kubernetes deployments. | E5: 0.75
A6: 1.1 | B6: What is Ansible?
B7: Overview of Ansible as an automation tool for configuration management, application deployment, and task automation.
B8: Comparison with other automation tools (Puppet, Chef, SaltStack).
A9: 1.2 | B9: Ansible Architecture
B10: Understanding Ansible's agentless architecture, modules, playbooks, and inventory files.
A11: 2 | B11: Setting Up Ansible
A12: 2.1 | B12: Installation
B13: Installing Ansible on various Linux distributions
A14: 2.2 | B14: Configuring Ansible
B15: Setting up Ansible configurations: ansible.cfg
B16: Managing inventory files for defining groups of hosts: /etc/ansible/hosts
A17: 3 | B17: Ansible Playbooks
A18: 3.1 | B18: Writing Your First Playbook
B19: Basic structure and syntax of playbooks.
B20: Running simple playbooks: ansible-playbook playbook.yml
A21: 3.2 | B21: Playbook Variables and Facts
B22: Using variables for dynamic playbook execution.
B23: Gathering system facts and using them in tasks.
A24: 3.3 | B24: Task Control
B25: Implementing task conditions, loops, and handlers.
A26: 4 | B26: Managing Infrastructure with Ansible
A27: 4.1 | B27: Configuring and Managing Servers
B28: Using Ansible modules like yum, apt, service, file, and user for server configuration and management.
A29: 4.2 | B29: Deploying Applications
B30: Automating deployment workflows with Ansible.
B31: Rolling updates and blue-green deployments.
A32: 5 | B32: Advanced Ansible Features | E32: 0.75
A33: 5.1 | B33: Roles and Reusability
B34: Structuring complex playbooks with roles.
B35: Sharing roles via Ansible Galaxy.
A36: 5.2 | B36: Ansible Vault
B37: Securing sensitive data with Ansible Vault: ansible-vault create secret.yml
A38: 5.3 | B38: Dynamic Inventory
B39: Working with dynamic inventory scripts for AWS, GCP, and other cloud providers.
A40: 6 | B40: Ansible for Network Automation
A41: 6.1 | B41: Network Modules
B42: Overview of Ansible's capabilities in network automation for various vendors (Cisco, Juniper, Arista).
A43: 6.2 | B43: Automating Network Configurations
B44: Examples of automating network device configurations and validations.
A45: 7 | B45: Ansible in Cloud Environments
A46: 7.1 | B46: Managing Cloud Resources
B47: Using Ansible to manage virtual machines, networking, and storage in cloud environments (AWS, Azure, GCP).
A48: 8 | B48: Ansible and Kubernetes
A49: 8.1 | B49: Orchestrating Kubernetes deployments with Ansible playbooks.

Sheet DevOps and Jenkins
A1: Module | B1: DevOps and Jenkins
A2: Duration (Days) | B2: =SUM(E5:E38) -> 1.5
A4: Sl. No. | B4: Topics | C4: Day End Assignment Options | D4: Remarks | E4: Duration (Days)
A5: 1 | B5: Introduction to DevOps | C5: Task 1: Create a Basic Jenkins Job Topic: Jenkins Essentials - Job Configuration in Jenkins Description: Set up a basic Jenkins job that pulls from a public Git repository and executes a simple shell command. Steps: Log into Jenkins with the provided credentials. Navigate to the Jenkins dashboard and select 'New Item'. Enter a name for the job, select 'Freestyle project', and click OK. In the Source Code Management section, select Git and enter the URL of a public repository (e.g., a GitHub repo URL). In the Build section, add a 'Execute shell' build step with a command like echo "Hello World". Save the job and click 'Build Now' to run it. Observe the build output to ensure the command executed successfully. Task 2: Configure Jenkins to Run a Simple Maven Build Topic: Building with Jenkins - Automating Builds Description: Configure Jenkins to build a Maven-based Java project. Steps: Create a new Jenkins job or select an existing job. Under the Build section, add a build step for 'Invoke top-level Maven targets'. In the Goals field, input clean install to run the corresponding Maven goals. Save the job and click 'Build Now'. After the build completes, check the console output for a 'BUILD SUCCESS' message. | D5: This module provides an Introduction to DevOps, emphasizing its principles, cultural aspects, and significance in software development. Learners explore the DevOps lifecycle, emphasizing automation's pivotal role. They delve into CI/CD fundamentals, constructing pipelines, and examining various tools. Specifically, they focus on Jenkins, covering installation, configuration, job creation, and build automation. Learners master integrating Jenkins with build tools like Maven or Gradle, managing artifacts, and configuring automated testing for unit and integration tests. This foundational knowledge empowers learners to streamline software development processes, fostering collaboration, efficiency, and quality in the DevOps environment. | E5: 0.75
A6: 1.1 | B6: DevOps Principles and Culture
B7: Key concepts in DevOps and its importance in software development
B8: The lifecycle of DevOps and the importance of automation
A9: 2 | B9: CI/CD Fundamentals
A10: 2.1 | B10: Building a CI/CD pipeline and understanding its components
B11: Overview of CI/CD tools and comparison
A12: 3 | B12: Jenkins for CI/CD
A13: 3.1 | B13: Jenkins Essentials
B14: Installing Jenkins and initial setup
B15: Overview of Jenkins features and architecture
A16: 3.2 | B16: Job Configuration in Jenkins
B17: Creating different types of Jenkins jobs
B18: Managing build triggers and notifications
A19: 4 | B19: Building with Jenkins
A20: 4.1 | B20: Automating Builds
B21: Integration with build tools (e.g., Maven, Gradle)
B22: Managing build artifacts and dependencies
A23: 4.2 | B23: Automated Testing
B24: Configuring Jenkins for automated testing (unit tests, integration tests)
A25: 5 | B25: Advanced Jenkins Features | D25: This module delves into Advanced Jenkins Features, focusing on Jenkins Pipeline creation with scripted and declarative Jenkinsfiles for managing complex workflows. Learners explore enhancing Jenkins functionality through plugins, integrating Jenkins with Docker for building and deploying containers, and orchestrating build agents with Kubernetes. They also master configuration management and deployment automation using Ansible and Jenkins integration. Security best practices for securing Jenkins and CI/CD pipelines are emphasized, including proper authentication, authorization, and infrastructure as code management. This comprehensive knowledge equips learners to implement robust, secure, and efficient CI/CD pipelines, enhancing their DevOps capabilities and workflow automation proficiency. | E25: 0.75
A26: 5.1 | B26: Jenkins Pipeline
B27: Writing Jenkinsfiles for scripted and declarative pipelines
B28: Pipeline management and complex workflows
A29: 5.2 | B29: Using Plugins for Enhancements
B30: Extending Jenkins with plugins for SCM, build and test tools, UI enhancements
A31: 6 | B31: Jenkins and Containers
A32: 6.1 | B32: Docker Integration
B33: Using Jenkins to build Docker images
B34: Deploying containers with Jenkins pipelines
A35: 6.2 | B35: Kubernetes Integration
B36: Orchestrating Jenkins build agents with Kubernetes
B37: Continuous Deployment to Kubernetes clusters
A38: 7 | B38: Configuration Management and Deployment
A39: 7.1 | B39: Ansible Integration
B40: Writing Ansible playbooks for environment provisioning
B41: Managing infrastructure as code and automating deployment with Ansible and Jenkins
A42: 8 | B42: Jenkins Security
A43: 8.1 | B43: Securing Jenkins with proper authentication and authorization
B44: Best practices for securing CI/CD pipelines

Sheet Capstone Project
A1: Module | B1: Capstone Project
A2: Duration (Days) | B2: 7
B3: Capstone Scenarios
B4: Assignment 1 | C4: Assignment 2 | D4: Assignment 3 | E4: Assignment 4 | F4: Assignment 5
B5: Simple E-Commerce Checkout Process Automation | C5: Health Reminder Application Testing | D5: Educational Quiz Application Testing | E5: Personal Budgeting App Testing | F5: Contact Management System Testing
B6: Objective: | C6: Objective: | D6: Objective: | E6: Objective: | F6: Objective:
B7: Automate the UI and API testing for an e-commerce checkout process to ensure reliability and efficiency of user transactions. | C7: Ensure the health reminder application functions correctly for user account creation, reminder setting, and notification delivery through UI and API test automation. | D7: Automate testing for an educational quiz application to verify the creation, participation, and result viewing functionalities are working as expected. | E7: Validate the functionality of a personal budgeting app, focusing on expense tracking, budget setting, and report generation through comprehensive UI and API testing. | F7: Ensure the contact management system's user interface and API function correctly for adding, editing, and deleting contacts, enhancing user experience and data integrity.
B8: Day 1: Set up the project environment. Install Selenium, Rest-Assured, and any necessary dependencies. Begin designing test cases for the UI flow. | C8: Day 1: Environment setup and planning. Install necessary tools and outline test scenarios. | D8: Day 1: Set up the development and test environment. Plan out the testing strategy and scenarios. | E8: Day 1: Initial setup, including tool installation and test planning. | F8: Day 1: Prepare the environment and outline detailed test cases.
B9: Day 2: Develop Selenium scripts to automate the process of adding a product to the cart and navigating to the checkout page. | C9: Day 2: Develop Selenium tests for account creation and setting reminders. | D9: Day 2: Develop Selenium tests for creating and participating in quizzes. | E9: Day 2: Start with Selenium automation for adding expenses and setting budgets. | F9: Day 2: Automate contact addition and editing features using Selenium.
B10: Day 3: Extend Selenium scripts to cover the checkout process, including form filling and order submission. | C10: Day 3: Continue with Selenium for testing notification functionalities. | D10: Day 3: Extend Selenium automation to cover viewing quiz results and additional quiz functionalities. | E10: Day 3: Complete UI testing with Selenium and start API testing with Rest-Assured for expense and budget management. | F10: Day 3: Finalize Selenium tests for deleting contacts and begin API testing with Rest-Assured.
B11: Day 4: Write Rest-Assured tests for product selection and order submission APIs. | C11: Day 4: Implement Rest-Assured tests for the reminder management APIs. | D11: Day 4: Write API tests with Rest-Assured for quiz creation, participation, and scoring. | E11: Day 4: Continue with API testing, focusing on reporting features. | F11: Day 4: Complete API testing for contact management.
B12: Day 5: Integrate tests with Jenkins for automatic execution upon code commits. Begin Docker containerization of the test environment. | C12: Day 5: Setup a basic Jenkins pipeline for running automated tests. Start with Docker basics. | D12: Day 5: Configure Jenkins to execute tests automatically. Begin Docker integration. | E12: Day 5: Setup a Jenkins pipeline for continuous testing. Begin learning Docker basics for containerization. | F12: Day 5: Configure Jenkins for automated test execution. Start with Docker containerization.
B13: Day 6: Finalize Docker setup. Conduct thorough testing and debugging of automated tests. | C13: Day 6: Finalize Docker containerization and ensure all tests run successfully within the containerized environment. | D13: Day 6: Complete Docker setup for the application and testing environment. Perform final testing and adjustments. | E13: Day 6: Finalize Docker containerization of the testing environment. Debug and refine tests. | F13: Day 6: Complete the Docker setup and ensure all automated tests are correctly running within the container.
